webchatter/__init__.py
webchatter/checkpoint.py
webchatter/request.py
webchatter/webchatter.py
webchatter-0.2.0.dist-info/AUTHORS.md
webchatter-0.2.0.dist-info/LICENSE
webchatter-0.2.0.dist-info/METADATA
webchatter-0.2.0.dist-info/WHEEL
webchatter-0.2.0.dist-info/top_level.txt
webchatter-0.2.0.dist-info/RECORD
